books/tmp_mealy.v
module mealyFSM (
	output	reg	o_d,
	input 		i_d,
	input		clk,
	input		reset_n
);
parameter	IDLE	=	2'b00;
parameter	S0		=	2'b01;
// inner state/next_state
reg [1:0] state, next_state;
reg o_d_next;
//state
always @(posedge clk or negedge reset_n) begin
	if (!reset_n) begin
		state	<=	IDLE;
	end else begin
		state	<=	next_state;
	end
end
//output
always @(*) begin
	o_d_next = 1'b0;
	case (state)
		IDLE: begin
			if (i_d == 1'b1) begin
				o_d_next = 1'b1;
			end
		end
	endcase
end
//next_state
always @(*) begin
	next_state = IDLE;
	case (state)
		IDLE: begin
			if (i_d == 1'b1) begin
				next_state = S0;
			end
		end
		S0: begin
			if (i_d == 1'b1) begin
				next_state = S0;
			end
		end
	endcase
end
// D-FF stores output
always @(posedge clk or negedge reset_n) begin
    if (!reset_n) begin
        o_d <= 1'b0;
    end else begin
        o_d <= o_d_next;
    end
end
endmodule

books/mealy_t.v
//-----------------------------------------------------
// Design Name : mealy_t
// File Name : mealy_t.v
// Function : Testing mealy.v design.
// Coder    : hydai
//-----------------------------------------------------

module mealy_t;

reg reset_n, clk;
reg i_d;
wire o_d;

mealyFSM fsm(
    .o_d(o_d),
    .i_d(i_d),
    .clk(clk),
    .reset_n(reset_n)
);

reg [59:0] testpattern;
integer i;
initial begin
    testpattern = 60'b00010001100000111000011111000001111110000010101010110110101;
    #0 reset_n = 1'b0; clk = 0;
    #30 reset_n = 1'b1; i_d = 0;
    $display("%t i_d = %b, o_d = %b", $time, i_d, o_d);
    for (i = 0; i < 60; i = i+1) begin
        #25 i_d = testpattern[i];
        $display("%t i_d = %b, o_d = %b", $time, i_d, o_d);
    end
    #100 $finish;
end

always begin
    #10 clk = ~clk;
end

initial begin
    $dumpfile("mealy_t.vcd");
    $dumpvars;
end

endmodule // End of mealy_t

books/mealy_t.vcd
$date
	Sat Jun  7 23:08:44 2014
$end
$version
	Icarus Verilog
$end
$timescale
	1s
$end
$scope module mealy_t $end
$var wire 1 ! o_d $end
$var reg 1 " clk $end
$var integer 32 # i [31:0] $end
$var reg 1 $ i_d $end
$var reg 1 % reset_n $end
$var reg 60 & testpattern [59:0] $end
$scope module fsm $end
$var wire 1 ' clk $end
$var wire 1 ( i_d $end
$var wire 1 ) reset_n $end
$var reg 2 * next_state [1:0] $end
$var reg 1 + o_d $end
$var reg 1 , o_d_next $end
$var reg 2 - state [1:0] $end
$upscope $end
$upscope $end
$enddefinitions $end
#0
$dumpvars
b0 -
0,
0+
b0 *
0)
x(
0'
b10001100000111000011111000001111110000010101010110110101 &
0%
x$
bx #
0"
0!
$end
#10
1"
1'
#20
0"
0'
#30
1"
1'
b0 #
0$
0(
1%
1)
#40
0"
0'
#50
1"
1'
#55
b1 *
1,
b1 #
1$
1(
#60
0"
0'
#70
0,
b1 *
b1 -
1+
1!
1"
1'
#80
b0 *
0"
0'
b10 #
0$
0(
#90
0+
0!
b0 -
1"
1'
#100
0"
0'
#105
b1 *
1,
b11 #
1$
1(
#110
0,
b1 *
b1 -
1+
1!
1"
1'
#120
0"
0'
#130
0+
0!
b0 -
b0 *
1"
1'
b100 #
0$
0(
#140
0"
0'
#150
1"
1'
#155
b1 *
1,
b101 #
1$
1(
#160
0"
0'
#170
0,
b1 *
1+
1!
b1 -
1"
1'
#180
0"
0'
b110 #
#190
0+
0!
1"
1'
#200
0"
0'
#205
b0 *
b111 #
0$
0(
#210
b0 -
1"
1'
#220
0"
0'
#230
b1 -
1+
1!
b1 *
0,
1"
1'
b1000 #
1$
1(
#240
0"
0'
#250
0+
0!
1"
1'
#255
b1001 #
#260
0"
0'
#270
1"
1'
#280
b0 *
0"
0'
b1010 #
0$
0(
#290
b0 -
1"
1'
#300
0"
0'
#305
b1 *
1,
b1011 #
1$
1(
#310
0,
b1 *
b1 -
1+
1!
1"
1'
#320
0"
0'
#330
0+
0!
b0 -
b0 *
1"
1'
b1100 #
0$
0(
#340
0"
0'
#350
1"
1'
#355
b1 *
1,
b1101 #
1$
1(
#360
0"
0'
#370
0,
b1 *
1+
1!
b1 -
1"
1'
#380
b0 *
0"
0'
b1110 #
0$
0(
#390
b0 -
0+
0!
1"
1'
#400
0"
0'
#405
b1 *
1,
b1111 #
1$
1(
#410
0,
b1 *
1+
1!
b1 -
1"
1'
#420
0"
0'
#430
b0 -
0+
0!
b0 *
1"
1'
b10000 #
0$
0(
#440
0"
0'
#450
1"
1'
#455
b1 *
1,
b10001 #
1$
1(
#460
0"
0'
#470
0,
b1 *
b1 -
1+
1!
1"
1'
#480
b0 *
0"
0'
b10010 #
0$
0(
#490
0+
0!
b0 -
1"
1'
#500
0"
0'
#505
b10011 #
#510
1"
1'
#520
0"
0'
#530
1"
1'
b10100 #
#540
0"
0'
#550
1"
1'
#555
b10101 #
#560
0"
0'
#570
1"
1'
#580
0"
0'
b10110 #
#590
1"
1'
#600
0"
0'
#605
b1 *
1,
b10111 #
1$
1(
#610
0,
b1 *
1+
1!
b1 -
1"
1'
#620
0"
0'
#630
0+
0!
1"
1'
b11000 #
#640
0"
0'
#650
1"
1'
#655
b11001 #
#660
0"
0'
#670
1"
1'
#680
0"
0'
b11010 #
#690
1"
1'
#700
0"
0'
#705
b11011 #
#710
1"
1'
#720
0"
0'
#730
1"
1'
b11100 #
#740
0"
0'
#750
1"
1'
#755
b0 *
b11101 #
0$
0(
#760
0"
0'
#770
b0 -
1"
1'
#780
0"
0'
b11110 #
#790
1"
1'
#800
0"
0'
#805
b11111 #
#810
1"
1'
#820
0"
0'
#830
1"
1'
b100000 #
#840
0"
0'
#850
1"
1'
#855
b100001 #
#860
0"
0'
#870
1"
1'
#880
b1 *
1,
0"
0'
b100010 #
1$
1(
#890
0,
b1 *
1+
1!
b1 -
1"
1'
#900
0"
0'
#905
b100011 #
#910
0+
0!
1"
1'
#920
0"
0'
#930
1"
1'
b100100 #
#940
0"
0'
#950
1"
1'
#955
b100101 #
#960
0"
0'
#970
1"
1'
#980
0"
0'
b100110 #
#990
1"
1'
#1000
0"
0'
#1005
b0 *
b100111 #
0$
0(
#1010
b0 -
1"
1'
#1020
0"
0'
#1030
1"
1'
b101000 #
#1040
0"
0'
#1050
1"
1'
#1055
b101001 #
#1060
0"
0'
#1070
1"
1'
#1080
0"
0'
b101010 #
#1090
1"
1'
#1100
0"
0'
#1105
b1 *
1,
b101011 #
1$
1(
#1110
0,
b1 *
b1 -
1+
1!
1"
1'
#1120
0"
0'
#1130
0+
0!
1"
1'
b101100 #
#1140
0"
0'
#1150
1"
1'
#1155
b101101 #
#1160
0"
0'
#1170
1"
1'
#1180
b0 *
0"
0'
b101110 #
0$
0(
#1190
b0 -
1"
1'
#1200
0"
0'
#1205
b101111 #
#1210
1"
1'
#1220
0"
0'
#1230
1"
1'
b110000 #
#1240
0"
0'
#1250
1"
1'
#1255
b110001 #
#1260
0"
0'
#1270
1"
1'
#1280
0"
0'
b110010 #
#1290
1"
1'
#1300
0"
0'
#1305
b1 *
1,
b110011 #
1$
1(
#1310
0,
b1 *
b1 -
1+
1!
1"
1'
#1320
0"
0'
#1330
0+
0!
1"
1'
b110100 #
#1340
0"
0'
#1350
1"
1'
#1355
b0 *
b110101 #
0$
0(
#1360
0"
0'
#1370
b0 -
1"
1'
#1380
0"
0'
b110110 #
#1390
1"
1'
#1400
0"
0'
#1405
b110111 #
#1410
1"
1'
#1420
0"
0'
#1430
b1 -
1+
1!
b1 *
0,
1"
1'
b111000 #
1$
1(
#1440
0"
0'
#1450
0+
0!
1"
1'
#1455
b0 *
b111001 #
0$
0(
#1460
0"
0'
#1470
b0 -
1"
1'
#1480
0"
0'
b111010 #
#1490
1"
1'
#1500
0"
0'
#1505
b111011 #
#1510
1"
1'
#1520
0"
0'
#1530
1"
1'
b111100 #
