books/moore.v
module mooreFSM (
	output	reg	o_d,
	input 		i_d,
	input		clk,
	input		reset_n
);
parameter	IDLE	=	2'b00;
parameter	S0		=	2'b01;
parameter	S1		=	2'b10;
// inner state/next_state
reg [1:0] state, next_state;
//state
always @(posedge clk or negedge reset_n) begin
	if (!reset_n) begin
		state	<=	IDLE;
	end else begin
		state	<=	next_state;
	end
end
//next_state
always @(*) begin
	case (state)
		IDLE: begin
			if (i_d == 1'b1) begin
				next_state = S0;
			end else begin
				next_state = IDLE;
			end
		end
		S0:	begin
			if (i_d == 1'b1) begin
				next_state = S1;
			end else begin
				next_state = IDLE;
			end
		end
		S1:	begin
			if (i_d == 1'b1) begin
				next_state = S1;
			end else begin
				next_state = IDLE;
			end
		end
		default:	begin
			next_state = IDLE;
		end
	endcase
end
//output
always @(*) begin
	o_d = 1'b0;
	case (state)
		S0: begin
			o_d = 1'b1;
		end
	endcase
end
endmodule

books/moore_t.v
//-----------------------------------------------------
// Design Name : moore_t
// File Name : moore_t.v
// Function : Testing moore.v design.
// Coder    : hydai
//-----------------------------------------------------

module moore_t;

reg reset_n, clk;
reg i_d;
wire o_d;

mooreFSM fsm(
    .o_d(o_d),
    .i_d(i_d),
    .clk(clk),
    .reset_n(reset_n)
);

reg [59:0] testpattern;
integer i;
initial begin
    testpattern = 60'b00010001100000111000011111000001111110000010101010110110101;
    #0 reset_n = 1'b0; clk = 0;
    #30 reset_n = 1'b1; i_d = 0;
    $display("%t i_d = %b, o_d = %b", $time, i_d, o_d);
    for (i = 0; i < 60; i = i+1) begin
        #20 i_d = testpattern[i];
        $display("%t i_d = %b, o_d = %b", $time, i_d, o_d);
    end
    #100 $finish;
end

always begin
    #10 clk = ~clk;
end

initial begin
    $dumpfile("moore_t.vcd");
    $dumpvars;
end

endmodule // End of moore_t

books/moore_t.vcd
$date
	Sat Jun  7 23:06:22 2014
$end
$version
	Icarus Verilog
$end
$timescale
	1s
$end
$scope module moore_t $end
$var wire 1 ! o_d $end
$var reg 1 " clk $end
$var integer 32 # i [31:0] $end
$var reg 1 $ i_d $end
$var reg 1 % reset_n $end
$var reg 60 & testpattern [59:0] $end
$scope module fsm $end
$var wire 1 ' clk $end
$var wire 1 ( i_d $end
$var wire 1 ) reset_n $end
$var reg 2 * next_state [1:0] $end
$var reg 1 + o_d $end
$var reg 2 , state [1:0] $end
$upscope $end
$upscope $end
$enddefinitions $end
#0
$dumpvars
b0 ,
0+
b0 *
0)
x(
0'
b10001100000111000011111000001111110000010101010110110101 &
0%
x$
bx #
0"
0!
$end
#10
1"
1'
#20
0"
0'
#30
1"
1'
b0 #
0$
0(
1%
1)
#40
0"
0'
#50
1+
1!
b1 ,
b10 *
1"
1'
b1 #
1$
1(
#60
0"
0'
#70
0+
0!
b0 ,
b0 *
1"
1'
b10 #
0$
0(
#80
0"
0'
#90
1+
1!
b1 ,
b10 *
1"
1'
b11 #
1$
1(
#100
0"
0'
#110
0+
0!
b0 ,
b0 *
1"
1'
b100 #
0$
0(
#120
0"
0'
#130
1+
1!
b1 ,
b10 *
1"
1'
b101 #
1$
1(
#140
0"
0'
#150
0+
0!
b10 ,
1"
1'
b110 #
#160
0"
0'
#170
b0 ,
b0 *
1"
1'
b111 #
0$
0(
#180
0"
0'
#190
1+
1!
b1 ,
b10 *
1"
1'
b1000 #
1$
1(
#200
0"
0'
#210
0+
0!
b10 ,
1"
1'
b1001 #
#220
0"
0'
#230
b0 ,
b0 *
1"
1'
b1010 #
0$
0(
#240
0"
0'
#250
1+
1!
b1 ,
b10 *
1"
1'
b1011 #
1$
1(
#260
0"
0'
#270
0+
0!
b0 ,
b0 *
1"
1'
b1100 #
0$
0(
#280
0"
0'
#290
1+
1!
b1 ,
b10 *
1"
1'
b1101 #
1$
1(
#300
0"
0'
#310
0+
0!
b0 ,
b0 *
1"
1'
b1110 #
0$
0(
#320
0"
0'
#330
1+
1!
b1 ,
b10 *
1"
1'
b1111 #
1$
1(
#340
0"
0'
#350
0+
0!
b0 ,
b0 *
1"
1'
b10000 #
0$
0(
#360
0"
0'
#370
1+
1!
b1 ,
b10 *
1"
1'
b10001 #
1$
1(
#380
0"
0'
#390
0+
0!
b0 ,
b0 *
1"
1'
b10010 #
0$
0(
#400
0"
0'
#410
1"
1'
b10011 #
#420
0"
0'
#430
1"
1'
b10100 #
#440
0"
0'
#450
1"
1'
b10101 #
#460
0"
0'
#470
1"
1'
b10110 #
#480
0"
0'
#490
1+
1!
b1 ,
b10 *
1"
1'
b10111 #
1$
1(
#500
0"
0'
#510
0+
0!
b10 ,
1"
1'
b11000 #
#520
0"
0'
#530
1"
1'
b11001 #
#540
0"
0'
#550
1"
1'
b11010 #
#560
0"
0'
#570
1"
1'
b11011 #
#580
0"
0'
#590
1"
1'
b11100 #
#600
0"
0'
#610
b0 ,
b0 *
1"
1'
b11101 #
0$
0(
#620
0"
0'
#630
1"
1'
b11110 #
#640
0"
0'
#650
1"
1'
b11111 #
#660
0"
0'
#670
1"
1'
b100000 #
#680
0"
0'
#690
1"
1'
b100001 #
#700
0"
0'
#710
1+
1!
b1 ,
b10 *
1"
1'
b100010 #
1$
1(
#720
0"
0'
#730
0+
0!
b10 ,
1"
1'
b100011 #
#740
0"
0'
#750
1"
1'
b100100 #
#760
0"
0'
#770
1"
1'
b100101 #
#780
0"
0'
#790
1"
1'
b100110 #
#800
0"
0'
#810
b0 ,
b0 *
1"
1'
b100111 #
0$
0(
#820
0"
0'
#830
1"
1'
b101000 #
#840
0"
0'
#850
1"
1'
b101001 #
#860
0"
0'
#870
1"
1'
b101010 #
#880
0"
0'
#890
1+
1!
b1 ,
b10 *
1"
1'
b101011 #
1$
1(
#900
0"
0'
#910
0+
0!
b10 ,
1"
1'
b101100 #
#920
0"
0'
#930
1"
1'
b101101 #
#940
0"
0'
#950
b0 ,
b0 *
1"
1'
b101110 #
0$
0(
#960
0"
0'
#970
1"
1'
b101111 #
#980
0"
0'
#990
1"
1'
b110000 #
#1000
0"
0'
#1010
1"
1'
b110001 #
#1020
0"
0'
#1030
1"
1'
b110010 #
#1040
0"
0'
#1050
1+
1!
b1 ,
b10 *
1"
1'
b110011 #
1$
1(
#1060
0"
0'
#1070
0+
0!
b10 ,
1"
1'
b110100 #
#1080
0"
0'
#1090
b0 ,
b0 *
1"
1'
b110101 #
0$
0(
#1100
0"
0'
#1110
1"
1'
b110110 #
#1120
0"
0'
#1130
1"
1'
b110111 #
#1140
0"
0'
#1150
1+
1!
b1 ,
b10 *
1"
1'
b111000 #
1$
1(
#1160
0"
0'
#1170
0+
0!
b0 ,
b0 *
1"
1'
b111001 #
0$
0(
#1180
0"
0'
#1190
1"
1'
b111010 #
#1200
0"
0'
#1210
1"
1'
b111011 #
#1220
0"
0'
#1230
1"
1'
b111100 #
